masked_input/__init__.py
masked_input/__main__.py
masked_input-1.0.2.dist-info/licenses/LICENSE
masked_input-1.0.2.dist-info/METADATA
masked_input-1.0.2.dist-info/WHEEL
masked_input-1.0.2.dist-info/top_level.txt
masked_input-1.0.2.dist-info/RECORD
