Metadata-Version: 2.4
Name: masked-input
Version: 1.0.2
Summary: Cross-platform library to read password input with various masking options.
Home-page: https://github.com/ree-verse/masked-input
Author: Ree-verse
Author-email: reeversesoft@gmail.com
License: MIT
Project-URL: Source, https://github.com/ree-verse/masked-input
Project-URL: Issues, https://github.com/ree-verse/masked-input/issues
Project-URL: Docs, https://github.com/ree-verse/masked-input/blob/main/README.md
Keywords: console,cross-platform,getpass,input,linux,macOS,mask,masked,masked-input,password,python,secure,security,shell,terminal,windows
Classifier: Development Status :: 5 - Production/Stable
Classifier: Environment :: Console
Classifier: Intended Audience :: Developers
Classifier: Intended Audience :: Information Technology
Classifier: Operating System :: OS Independent
Classifier: Operating System :: Microsoft :: Windows
Classifier: Operating System :: POSIX :: Linux
Classifier: Operating System :: MacOS :: MacOS X
Classifier: Programming Language :: Python
Classifier: Programming Language :: Python :: 3.9
Classifier: Programming Language :: Python :: 3.10
Classifier: Programming Language :: Python :: 3.11
Classifier: Programming Language :: Python :: 3.12
Classifier: Topic :: Software Development :: Libraries :: Python Modules
Classifier: Topic :: System :: Shells
Classifier: Topic :: Security
Classifier: Topic :: Terminals
Classifier: Topic :: Utilities
Classifier: Typing :: Typed
Requires-Python: >=3.9
License-File: LICENSE
Dynamic: author
Dynamic: author-email
Dynamic: classifier
Dynamic: description
Dynamic: description-content-type
Dynamic: home-page
Dynamic: keywords
Dynamic: license
Dynamic: license-file
Dynamic: project-url
Dynamic: requires-python
Dynamic: summary
